mbr_test_pckg/__init__.py
mbr_test_pckg/__main__.py
mbr_test_pckg/show.py
mbr_test_pckg_yurii_1-1.1.1.dist-info/METADATA
mbr_test_pckg_yurii_1-1.1.1.dist-info/WHEEL
mbr_test_pckg_yurii_1-1.1.1.dist-info/entry_points.txt
mbr_test_pckg_yurii_1-1.1.1.dist-info/top_level.txt
mbr_test_pckg_yurii_1-1.1.1.dist-info/RECORD
