Metadata-Version: 2.4
Name: mbr-test-pckg-Yurii-1
Version: 1.1.1
Summary: My test package.
Author-email: Yurii Oros <noemail@gmail.com>
